url_widget/__init__.py
url_widget/_frontend.py
url_widget/_v.py
url_widget/_version.py
url_widget/url.py
url_widget/labextension/package.json
url_widget/labextension/static/480.0dd5b02434d0c3b1758b.js
url_widget/labextension/static/480.14621226a535e3e64970.js
url_widget/labextension/static/480.1f3c728b726c75d23b2f.js
url_widget/labextension/static/480.21ee07d1702fb5399854.js
url_widget/labextension/static/480.32495ee1d8f5b4faf524.js
url_widget/labextension/static/480.779e8ea371e769f35804.js
url_widget/labextension/static/480.9135036a3a47fd29045d.js
url_widget/labextension/static/480.cd171381b1c51f4f9112.js
url_widget/labextension/static/480.fd52f4e1c4147c66e4ed.js
url_widget/labextension/static/568.051d3decc980cf2db703.js
url_widget/labextension/static/568.21e759d8de6afd1e097b.js
url_widget/labextension/static/568.55db3ebd224112c76644.js
url_widget/labextension/static/568.5716ee704e36d5517e9f.js
url_widget/labextension/static/568.9333b9924f74878bba12.js
url_widget/labextension/static/568.aa4258dad969dceaee19.js
url_widget/labextension/static/568.cae17d2fc45d05333851.js
url_widget/labextension/static/568.cb484884fe55e1ca7060.js
url_widget/labextension/static/568.dd01bd1fe5a7269da18f.js
url_widget/labextension/static/remoteEntry.110fa759591fdbf668a4.js
url_widget/labextension/static/remoteEntry.2cd8b377f6b6f0c37b45.js
url_widget/labextension/static/remoteEntry.33aa1a5dac795862be8d.js
url_widget/labextension/static/remoteEntry.5665df1ad87567ecff58.js
url_widget/labextension/static/remoteEntry.5751146be3feac486a96.js
url_widget/labextension/static/remoteEntry.81bb82caabcb0364c339.js
url_widget/labextension/static/remoteEntry.ab06ee82a49e27eabb7e.js
url_widget/labextension/static/remoteEntry.cc007b2d0cd8aa688570.js
url_widget/labextension/static/remoteEntry.fe8eb46e1e7de0c16af5.js
url_widget/labextension/static/style.js
url_widget/labextension/static/third-party-licenses.json
url_widget/nbextension/extension.js
url_widget/nbextension/index.js
url_widget-0.0.0.dist-info/LICENSE.txt
url_widget-0.0.0.dist-info/METADATA
url_widget-0.0.0.dist-info/WHEEL
url_widget-0.0.0.dist-info/top_level.txt
url_widget-0.0.0.dist-info/RECORD
